pytchat/__init__.py
pytchat/api.py
pytchat/exceptions.py
pytchat/config/__init__.py
pytchat/config/mylogger.py
pytchat/core/__init__.py
pytchat/core/pytchat.py
pytchat/core_async/__init__.py
pytchat/core_async/buffer.py
pytchat/core_async/livechat.py
pytchat/core_multithread/__init__.py
pytchat/core_multithread/buffer.py
pytchat/core_multithread/livechat.py
pytchat/paramgen/__init__.py
pytchat/paramgen/arcparam.py
pytchat/paramgen/enc.py
pytchat/paramgen/liveparam.py
pytchat/parser/__init__.py
pytchat/parser/live.py
pytchat/processors/__init__.py
pytchat/processors/chat_processor.py
pytchat/processors/combinator.py
pytchat/processors/dummy_processor.py
pytchat/processors/html_archiver.py
pytchat/processors/jsonfile_archiver.py
pytchat/processors/simple_display_processor.py
pytchat/processors/tsv_archiver.py
pytchat/processors/compatible/__init__.py
pytchat/processors/compatible/processor.py
pytchat/processors/compatible/renderer/__init__.py
pytchat/processors/compatible/renderer/base.py
pytchat/processors/compatible/renderer/currency.py
pytchat/processors/compatible/renderer/legacypaid.py
pytchat/processors/compatible/renderer/membership.py
pytchat/processors/compatible/renderer/paidmessage.py
pytchat/processors/compatible/renderer/paidsticker.py
pytchat/processors/compatible/renderer/textmessage.py
pytchat/processors/default/__init__.py
pytchat/processors/default/custom_encoder.py
pytchat/processors/default/processor.py
pytchat/processors/default/renderer/__init__.py
pytchat/processors/default/renderer/base.py
pytchat/processors/default/renderer/currency.py
pytchat/processors/default/renderer/legacypaid.py
pytchat/processors/default/renderer/membership.py
pytchat/processors/default/renderer/paidmessage.py
pytchat/processors/default/renderer/paidsticker.py
pytchat/processors/default/renderer/textmessage.py
pytchat/processors/speed/__init__.py
pytchat/processors/speed/calculator.py
pytchat/processors/superchat/__init__.py
pytchat/processors/superchat/calculator.py
pytchat-0.5.4.dist-info/LICENSE
pytchat-0.5.4.dist-info/METADATA
pytchat-0.5.4.dist-info/WHEEL
pytchat-0.5.4.dist-info/top_level.txt
pytchat-0.5.4.dist-info/RECORD
