Metadata-Version: 2.1
Name: pytchat
Version: 0.5.4
Summary: a python library for fetching youtube live chat.
Home-page: https://github.com/taizan-hokuto/pytchat
Author: taizan-hokuto
Author-email: 55448286+taizan-hokuto@users.noreply.github.com
License: MIT
Keywords: youtube livechat asyncio
Platform: UNKNOWN
Classifier: Natural Language :: Japanese
Classifier: Development Status :: 4 - Beta
Classifier: Programming Language :: Python
Classifier: Programming Language :: Python :: 3.7
Classifier: Programming Language :: Python :: 3.8
Classifier: License :: OSI Approved :: MIT License
Requires-Dist: httpx[http2] (==0.16.1)
